<?xml version="1.0" encoding="UTF-8"?>
<ksj:Dataset gml:id="A09Dataset" xmlns:ksj="http://nlftp.mlit.go.jp/ksj/schemas/ksj-app" xmlns:gml="http://www.opengis.net/gml/3.2" xmlns:xlink="http://www.w3.org/1999/xlink" xmlns:xsi="http://www.w3.org/2001/XMLSchema-instance" xmlns:schemaLocation="http://nlftp.mlit.go.jp/ksj/schemas/ksj-app KsjAppSchema-A09-v1_0.xsd">
<gml:description>国土数値情報（都市地域）データ　2018年度</gml:description>
<gml:boundedBy>
	<gml:EnvelopeWithTimePeriod srsName="JGD2011 / (B, L)" frame="GC / JST">
		<gml:lowerCorner>20.0 123.0</gml:lowerCorner>
		<gml:upperCorner>46.0 154.0</gml:upperCorner>
		<gml:beginPosition calendarEraName="西暦">1900</gml:beginPosition>
		<gml:endPosition indeterminatePosition="unknown"/>
	</gml:EnvelopeWithTimePeriod>
</gml:boundedBy>
	<gml:Curve gml:id="cv1_0">
		<gml:segments>
			<gml:LineStringSegment>
				<gml:posList>
				43.46178235 142.45203582
				43.46613350 142.45583303
				43.46452425 142.45947358
				43.46459287 142.46100048
				43.46487080 142.46127154
				43.46476100 142.46199210
				43.46498060 142.46220484
				43.46471983 142.46248963
				43.46454140 142.46252738
				43.46439043 142.46253081
				43.46406789 142.46252051
				43.46388604 142.46249649
				43.46372134 142.46245532
				43.46348115 142.46234552
				43.46323067 142.46230435
				43.46296646 142.46224258
				43.46265422 142.46214651
				43.46240031 142.46214994
				43.46220130 142.46207445
				43.46208121 142.46199553
				43.46200572 142.46195779
				43.46181014 142.46199210
				43.46165916 142.46203671
				43.46149446 142.46211906
				43.46128194 142.46230066
				43.46106725 142.46245069
				43.46071622 142.46248094
				43.46058128 142.46254911
				43.46044578 142.46265328
				43.46034402 142.46264618
				43.46027878 142.46266084
				43.46013147 142.46264423
				43.45997808 142.46260928
				43.45981067 142.46253036
				43.45971708 142.46244160
				43.45954552 142.46233866
				43.45936024 142.46219455
				43.45920240 142.46202985
				43.45904799 142.46182397
				43.45885928 142.46152202
				43.45822107 142.46033482
				43.45780589 142.45952504
				43.46175270 142.45758948
				43.46178235 142.45203582
				</gml:posList>
			</gml:LineStringSegment>
		</gml:segments>
	</gml:Curve>
	<gml:OrientableCurve gml:id="_cv1_0" orientation="+">
		<gml:baseCurve xlink:href="#cv1_0"/>
	</gml:OrientableCurve>
	<gml:Surface gml:id="sf1">
		<gml:patches>
			<gml:PolygonPatch>
				<gml:exterior>
					<gml:Ring>
						<gml:curveMember xlink:href="#_cv1_0"/>
					</gml:Ring>
				</gml:exterior>
			</gml:PolygonPatch>
		</gml:patches>
	</gml:Surface>
	<gml:Curve gml:id="cv2_0">
		<gml:segments>
			<gml:LineStringSegment>
				<gml:posList>
				43.46954160 142.45920005
				43.46969267 142.45918567
				43.46985093 142.45921444
				43.46998042 142.45928638
				43.47010272 142.45937990
				43.47293709 142.46184020
				43.47024872 142.46759226
				43.46804144 142.46803074
				43.46796659 142.46818968
				43.46476244 142.47504528
				43.46342836 142.47386765
				43.46069999 142.47960215
				43.46125552 142.48007704
				43.45990702 142.48300701
				43.46075844 142.48373824
				43.45944420 142.48658459
				43.45659469 142.48412459
				43.45487793 142.48269027
				43.45485349 142.48267996
				43.45470116 142.48232156
				43.45450852 142.48202139
				43.45435172 142.48157786
				43.45427108 142.48144794
				43.45400675 142.48122842
				43.45340642 142.48253212
				43.45198624 142.48132250
				43.45104782 142.48330930
				43.44682587 142.47961236
				43.45223069 142.46807813
				43.44836430 142.46466010
				43.44819551 142.46451241
				43.44812694 142.46436999
				43.44812694 142.46413790
				43.44816914 142.46380560
				43.44840650 142.46380560
				43.44855419 142.46380560
				43.44884431 142.46376867
				43.44906584 142.46371593
				43.45061662 142.46500824
				43.45099640 142.46418010
				43.45176651 142.46483944
				43.45217794 142.46397439
				43.45357575 142.46522450
				43.45571729 142.46057218
				43.45706762 142.45991811
				43.45886123 142.46315492
				43.45899122 142.46335316
				43.45910171 142.46347340
				43.45924795 142.46360339
				43.45936169 142.46366513
				43.45954693 142.46374962
				43.45969317 142.46376912
				43.45987190 142.46378212
				43.46001814 142.46373663
				43.46030087 142.46364888
				43.46055435 142.46357739
				43.46154877 142.46309643
				43.46162026 142.46303793
				43.46178925 142.46299894
				43.46195498 142.46299894
				43.46214997 142.46304118
				43.46308589 142.46329791
				43.46354700 142.46348438
				43.46428011 142.46351974
				43.46461956 142.46350560
				43.46477986 142.46351031
				43.46483879 142.46349853
				43.46507923 142.46341838
				43.46522774 142.46335002
				43.46544932 142.46322037
				43.46568977 142.46303886
				43.46587274 142.46285453
				43.46598064 142.46266749
				43.46625401 142.46217831
				43.46653457 142.46165316
				43.46670722 142.46142295
				43.46703814 142.46096974
				43.46731151 142.46053811
				43.46760645 142.45986908
				43.46777191 142.45954536
				43.46790140 142.45939429
				43.46801650 142.45935832
				43.46817477 142.45935832
				43.46844094 142.45936551
				43.46864956 142.45935113
				43.46954160 142.45920005
				</gml:posList>
			</gml:LineStringSegment>
		</gml:segments>
	</gml:Curve>
	<gml:OrientableCurve gml:id="_cv2_0" orientation="+">
		<gml:baseCurve xlink:href="#cv2_0"/>
	</gml:OrientableCurve>
	<gml:Surface gml:id="sf2">
		<gml:patches>
			<gml:PolygonPatch>
				<gml:exterior>
					<gml:Ring>
						<gml:curveMember xlink:href="#_cv2_0"/>
					</gml:Ring>
				</gml:exterior>
			</gml:PolygonPatch>
		</gml:patches>
	</gml:Surface>
	<gml:Curve gml:id="cv3_0">
		<gml:segments>
			<gml:LineStringSegment>
				<gml:posList>
				43.45328072 142.45313611
				43.45882797 142.44133697
				43.47267864 142.45364426
				43.47280899 142.45360409
				43.47995469 142.45085573
				43.48032951 142.45103128
				43.48318097 142.45263968
				43.48766039 142.45527230
				43.48776461 142.45537495
				43.48692778 142.45714759
				43.48670660 142.45773740
				43.48306454 142.46538523
				43.48200104 142.46588964
				43.48105489 142.46636272
				43.48048966 142.46657161
				43.47972168 142.46671292
				43.47907044 142.46670677
				43.47860965 142.46664533
				43.47781709 142.46645487
				43.47730101 142.46636886
				43.47670506 142.46633814
				43.46928899 142.48255397
				43.46770039 142.48125343
				43.46759159 142.48166942
				43.46750839 142.48204701
				43.46739320 142.48253340
				43.46733560 142.48287259
				43.46734200 142.48317338
				43.46738040 142.48341657
				43.46750199 142.48380696
				43.46757879 142.48414615
				43.46759159 142.48438935
				43.46756599 142.48461974
				43.46754039 142.48483733
				43.46742520 142.48539412
				43.46719480 142.48639889
				43.46707961 142.48690447
				43.46704121 142.48722447
				43.46691961 142.48808204
				43.46684281 142.48867722
				43.46677881 142.48934281
				43.46211974 142.48511892
				43.45945742 142.49083396
				43.45587352 142.48774925
				43.45612711 142.48887002
				43.45619111 142.48960600
				43.45613511 142.49039798
				43.45587912 142.49134195
				43.45545513 142.49241392
				43.45493515 142.49377388
				43.45452716 142.49464586
				43.43570369 142.47803032
				43.44955130 142.44849516
				43.44970329 142.44833516
				43.45041527 142.44916714
				43.45098326 142.44997511
				43.45123125 142.45036710
				43.45194048 142.45123338
				43.45278768 142.45219864
				43.45299601 142.45253890
				43.45316961 142.45283751
				43.45328072 142.45313611
				</gml:posList>
			</gml:LineStringSegment>
		</gml:segments>
	</gml:Curve>
	<gml:OrientableCurve gml:id="_cv3_0" orientation="+">
		<gml:baseCurve xlink:href="#cv3_0"/>
	</gml:OrientableCurve>
	<gml:Curve gml:id="cv3_1">
		<gml:segments>
			<gml:LineStringSegment>
				<gml:posList>
				43.46969267 142.45918567
				43.46954160 142.45920005
				43.46864956 142.45935113
				43.46844094 142.45936551
				43.46817477 142.45935832
				43.46801650 142.45935832
				43.46790140 142.45939429
				43.46777191 142.45954536
				43.46760645 142.45986908
				43.46731151 142.46053811
				43.46703814 142.46096974
				43.46670722 142.46142295
				43.46653457 142.46165316
				43.46625401 142.46217831
				43.46598064 142.46266749
				43.46587274 142.46285453
				43.46568977 142.46303886
				43.46544932 142.46322037
				43.46522774 142.46335002
				43.46507923 142.46341838
				43.46483879 142.46349853
				43.46477986 142.46351031
				43.46461956 142.46350560
				43.46428011 142.46351974
				43.46354700 142.46348438
				43.46308589 142.46329791
				43.46214997 142.46304118
				43.46195498 142.46299894
				43.46178925 142.46299894
				43.46162026 142.46303793
				43.46154877 142.46309643
				43.46055435 142.46357739
				43.46030087 142.46364888
				43.46001814 142.46373663
				43.45987190 142.46378212
				43.45969317 142.46376912
				43.45954693 142.46374962
				43.45936169 142.46366513
				43.45924795 142.46360339
				43.45910171 142.46347340
				43.45899122 142.46335316
				43.45886123 142.46315492
				43.45706762 142.45991811
				43.45571729 142.46057218
				43.45357575 142.46522450
				43.45217794 142.46397439
				43.45176651 142.46483944
				43.45099640 142.46418010
				43.45061662 142.46500824
				43.44906584 142.46371593
				43.44884431 142.46376867
				43.44855419 142.46380560
				43.44840650 142.46380560
				43.44816914 142.46380560
				43.44812694 142.46413790
				43.44812694 142.46436999
				43.44819551 142.46451241
				43.44836430 142.46466010
				43.45223069 142.46807813
				43.44682587 142.47961236
				43.45104782 142.48330930
				43.45198624 142.48132250
				43.45340642 142.48253212
				43.45400675 142.48122842
				43.45427108 142.48144794
				43.45435172 142.48157786
				43.45450852 142.48202139
				43.45470116 142.48232156
				43.45485349 142.48267996
				43.45487793 142.48269027
				43.45659469 142.48412459
				43.45944420 142.48658459
				43.46075844 142.48373824
				43.45990702 142.48300701
				43.46125552 142.48007704
				43.46069999 142.47960215
				43.46342836 142.47386765
				43.46476244 142.47504528
				43.46796659 142.46818968
				43.46804144 142.46803074
				43.47024872 142.46759226
				43.47293709 142.46184020
				43.47010272 142.45937990
				43.46998042 142.45928638
				43.46985093 142.45921444
				43.46969267 142.45918567
				</gml:posList>
			</gml:LineStringSegment>
		</gml:segments>
	</gml:Curve>
	<gml:OrientableCurve gml:id="_cv3_1" orientation="+">
		<gml:baseCurve xlink:href="#cv3_1"/>
	</gml:OrientableCurve>
	<gml:Curve gml:id="cv3_2">
		<gml:segments>
			<gml:LineStringSegment>
				<gml:posList>
				43.46613350 142.45583303
				43.46178235 142.45203582
				43.46175270 142.45758948
				43.45780589 142.45952504
				43.45822107 142.46033482
				43.45885928 142.46152202
				43.45904799 142.46182397
				43.45920240 142.46202985
				43.45936024 142.46219455
				43.45954552 142.46233866
				43.45971708 142.46244160
				43.45981067 142.46253036
				43.45997808 142.46260928
				43.46013147 142.46264423
				43.46027878 142.46266084
				43.46034402 142.46264618
				43.46044578 142.46265328
				43.46058128 142.46254911
				43.46071622 142.46248094
				43.46106725 142.46245069
				43.46128194 142.46230066
				43.46149446 142.46211906
				43.46165916 142.46203671
				43.46181014 142.46199210
				43.46200572 142.46195779
				43.46208121 142.46199553
				43.46220130 142.46207445
				43.46240031 142.46214994
				43.46265422 142.46214651
				43.46296646 142.46224258
				43.46323067 142.46230435
				43.46348115 142.46234552
				43.46372134 142.46245532
				43.46388604 142.46249649
				43.46406789 142.46252051
				43.46439043 142.46253081
				43.46454140 142.46252738
				43.46471983 142.46248963
				43.46498060 142.46220484
				43.46476100 142.46199210
				43.46487080 142.46127154
				43.46459287 142.46100048
				43.46452425 142.45947358
				43.46613350 142.45583303
				</gml:posList>
			</gml:LineStringSegment>
		</gml:segments>
	</gml:Curve>
	<gml:OrientableCurve gml:id="_cv3_2" orientation="+">
		<gml:baseCurve xlink:href="#cv3_2"/>
	</gml:OrientableCurve>
	<gml:Surface gml:id="sf3">
		<gml:patches>
			<gml:PolygonPatch>
				<gml:exterior>
					<gml:Ring>
						<gml:curveMember xlink:href="#_cv3_0"/>
					</gml:Ring>
				</gml:exterior>
				<gml:interior>
					<gml:Ring>
						<gml:curveMember xlink:href="#_cv3_1"/>
					</gml:Ring>
				</gml:interior>
				<gml:interior>
					<gml:Ring>
						<gml:curveMember xlink:href="#_cv3_2"/>
					</gml:Ring>
				</gml:interior>
			</gml:PolygonPatch>
		</gml:patches>
	</gml:Surface>
	<ksj:UrbanArea gml:id="ua1">
		<ksj:bounds xlink:href="#sf1"/>
		<ksj:prefectureCode>1</ksj:prefectureCode>
		<ksj:cityCode>1460</ksj:cityCode>
		<ksj:urbanAreaCode>3</ksj:urbanAreaCode>
	</ksj:UrbanArea>
	<ksj:UrbanArea gml:id="ua2">
		<ksj:bounds xlink:href="#sf2"/>
		<ksj:prefectureCode>1</ksj:prefectureCode>
		<ksj:cityCode>1460</ksj:cityCode>
		<ksj:urbanAreaCode>3</ksj:urbanAreaCode>
	</ksj:UrbanArea>
	<ksj:UrbanArea gml:id="ua3">
		<ksj:bounds xlink:href="#sf3"/>
		<ksj:prefectureCode>1</ksj:prefectureCode>
		<ksj:cityCode>1460</ksj:cityCode>
		<ksj:urbanAreaCode>4</ksj:urbanAreaCode>
	</ksj:UrbanArea>
</ksj:Dataset>
